findmypy/AppleCA.pem
findmypy/__init__.py
findmypy/base.py
findmypy/exceptions.py
findmypy-0.1.11.dist-info/LICENSE
findmypy-0.1.11.dist-info/METADATA
findmypy-0.1.11.dist-info/WHEEL
findmypy-0.1.11.dist-info/top_level.txt
findmypy-0.1.11.dist-info/RECORD
