Metadata-Version: 2.1
Name: findmypy
Version: 0.1.11
Summary: Library to use Apple's FindMy Api.
Home-page: https://github.com/LoPablo/findmypy
Author: LoPablo
Author-email: lopablo@protonmail.com
License: MIT
Keywords: icloud,find-my-iphone
Platform: UNKNOWN
Classifier: Development Status :: 3 - Alpha
Classifier: Intended Audience :: Developers
Classifier: License :: OSI Approved :: MIT License
Classifier: Operating System :: OS Independent
Classifier: Programming Language :: Python
Classifier: Programming Language :: Python :: 3 :: Only
Classifier: Programming Language :: Python :: 3
Classifier: Programming Language :: Python :: 3.7
Classifier: Programming Language :: Python :: 3.8
Classifier: Programming Language :: Python :: 3.9
Classifier: Programming Language :: Python :: 3.10
Classifier: Topic :: Software Development :: Libraries
Requires-Python: >=3.7
License-File: LICENSE
